dsl/__init__.py
dsl/config.default.yml
dsl/config.py
dsl/dsl.py
dsl/feature_extraction/__init__.py
dsl/feature_extraction/column_base/__init__.py
dsl/feature_extraction/column_base/column_name.py
dsl/feature_extraction/column_base/numeric.py
dsl/feature_extraction/column_base/textual.py
dsl/generate_train_data.py
dsl/input.py
dsl/sm_type_db.py
dsl/sm_type_db_v2.py
dsl2-1.3.5.dist-info/LICENSE
dsl2-1.3.5.dist-info/METADATA
dsl2-1.3.5.dist-info/WHEEL
dsl2-1.3.5.dist-info/RECORD
