Metadata-Version: 2.1
Name: dsl2
Version: 1.3.5
Summary: An implementation of Semantic labeling: A domain-independent approach
Home-page: https://github.com/binh-vu/dsl
License: MIT
Author: Binh Vu
Author-email: binh@toan2.com
Requires-Python: >=3.11,<4.0
Classifier: License :: OSI Approved :: MIT License
Classifier: Programming Language :: Python :: 3
Classifier: Programming Language :: Python :: 3.11
Classifier: Programming Language :: Python :: 3.12
Classifier: Programming Language :: Python :: 3.13
Requires-Dist: fastnumbers (>=5.0.1,<6.0.0)
Requires-Dist: ftfy (>=6.1.3,<7.0.0)
Requires-Dist: kgdata (>=7.0.0,<8.0.0)
Requires-Dist: numpy (>=2.1.1,<3.0.0)
Requires-Dist: scikit-learn (>=1.3.2,<2.0.0)
Requires-Dist: scipy (>=1.11.4,<2.0.0)
Requires-Dist: sem-desc (>=6.7.2,<7.0.0)
Requires-Dist: serde2 (>=1.6.0,<2.0.0)
Requires-Dist: spacy (>=3.7.2,<4.0.0)
Requires-Dist: tqdm (>=4.66.1,<5.0.0)
Project-URL: Repository, https://github.com/binh-vu/dsl
